LICENSE
certbot_dns_google_domains/__init__.py
certbot_dns_google_domains/dns_google_domains.py
certbot_dns_google_domains/test_dns_google_domains.py
certbot_dns_google_domains-0.1.11.dist-info/LICENSE
certbot_dns_google_domains-0.1.11.dist-info/METADATA
certbot_dns_google_domains-0.1.11.dist-info/WHEEL
certbot_dns_google_domains-0.1.11.dist-info/entry_points.txt
certbot_dns_google_domains-0.1.11.dist-info/RECORD
