Metadata-Version: 2.1
Name: certbot-dns-google-domains
Version: 0.1.11
Summary: Certbot DNS authenticator for Google Domains
License: Apache 2.0
Author: Amir Omidi
Author-email: amir@aaomidi.com
Requires-Python: >=3.7.2
Classifier: License :: Other/Proprietary License
Classifier: Programming Language :: Python :: 3
Classifier: Programming Language :: Python :: 3.8
Classifier: Programming Language :: Python :: 3.9
Classifier: Programming Language :: Python :: 3.10
Classifier: Programming Language :: Python :: 3.11
Requires-Dist: certbot (>=1.23.0)
Requires-Dist: dataclasses-json (>=0.5.7,<0.6.0)
Requires-Dist: publicsuffixlist (>=0.9.3,<0.10.0)
Requires-Dist: zope.interface (>=5.5.0)
